nineties/__init__.py
nineties/__main__.py
nineties/cli.py
nineties/nineties.py
nineties/parser.py
nineties/privacy.py
test/__init__.py
test/context.py
test/test_cli.py
test/test_nineties.py
test/test_parser.py
test/test_privacy.py
nineties-2022.7.24.dist-info/LICENSE
nineties-2022.7.24.dist-info/METADATA
nineties-2022.7.24.dist-info/WHEEL
nineties-2022.7.24.dist-info/entry_points.txt
nineties-2022.7.24.dist-info/top_level.txt
nineties-2022.7.24.dist-info/RECORD
