Metadata-Version: 2.1
Name: nineties
Version: 2022.7.24
Summary: Ease the reading of relics from the Nineties.
Home-page: https://git.sr.ht/~sthagen/nineties
Author: Stefan Hagen
Author-email: stefan@hagen.link
Maintainer: Stefan Hagen
Maintainer-email: stefan@hagen.link
Project-URL: Bug Tracker, https://todo.sr.ht/~sthagen/nineties
Project-URL: Documentation, https://codes.dilettant.life/docs/nineties
Project-URL: Source Code, https://git.sr.ht/~sthagen/nineties
Project-URL: Test Coverage, https://codes.dilettant.life/coverage/nineties
Keywords: developer-tools,sloc,taxonomies
Classifier: Development Status :: 3 - Alpha
Classifier: Intended Audience :: Developers
Classifier: License :: OSI Approved :: MIT License
Classifier: Programming Language :: Python :: 3.10
Classifier: Programming Language :: Python :: 3.8
Classifier: Programming Language :: Python :: 3.9
Requires-Python: >=3.8
License-File: LICENSE
Requires-Dist: faker (>=13.15.1)
Provides-Extra: dev
Requires-Dist: black ; extra == 'dev'
Requires-Dist: coverage ; extra == 'dev'
Requires-Dist: flake8 ; extra == 'dev'
Requires-Dist: mypy ; extra == 'dev'
Requires-Dist: pytest ; extra == 'dev'
Requires-Dist: pytest-cov ; extra == 'dev'
Requires-Dist: pytest-flake8 ; extra == 'dev'
